minibatch/VERSION
minibatch/__init__.py
minibatch/__main__.py
minibatch/_version.py
minibatch/marshaller.py
minibatch/models.py
minibatch/window.py
minibatch/contrib/__init__.py
minibatch/contrib/celery.py
minibatch/contrib/kafka.py
minibatch/contrib/mongodb.py
minibatch/contrib/mqtt.py
minibatch/contrib/omegaml.py
minibatch/contrib/apps/__init__.py
minibatch/contrib/apps/omegaml.py
minibatch/emitter/__init__.py
minibatch/emitter/base.py
minibatch/example/__init__.py
minibatch/example/util.py
minibatch/example/basic/__init__.py
minibatch/example/basic/__main__.py
minibatch/example/kafka/__init__.py
minibatch/example/mongodb/__init__.py
minibatch/example/mongodb/__main__.py
minibatch/example/mqtt/__init__.py
minibatch/example/mqtt/__main__.py
minibatch/tests/__init__.py
minibatch/tests/test_celery.py
minibatch/tests/test_kafka.py
minibatch/tests/test_minibatch.py
minibatch/tests/test_mongodb.py
minibatch/tests/test_mqtt.py
minibatch/tests/test_omegaml.py
minibatch/tests/util.py
minibatch-0.6.0.dist-info/licenses/LICENSE
minibatch-0.6.0.dist-info/licenses/LICENSE-NOSELLCLAUSE
minibatch-0.6.0.dist-info/licenses/NOTICE
minibatch-0.6.0.dist-info/METADATA
minibatch-0.6.0.dist-info/WHEEL
minibatch-0.6.0.dist-info/top_level.txt
minibatch-0.6.0.dist-info/RECORD
