Metadata-Version: 2.4
Name: minibatch
Version: 0.6.0
Summary: Python stream processing for humans
Home-page: http://github.com/omegaml/minibatch
Author: Patrick Senti
Author-email: patrick.senti@omegaml.io
License: Apache 2.0 + "No Sell, Consulting Yes" License Condition
License-File: LICENSE
License-File: LICENSE-NOSELLCLAUSE
License-File: NOTICE
Requires-Dist: mongoengine>=0.23.0
Requires-Dist: dill
Provides-Extra: apps
Requires-Dist: flask; extra == "apps"
Requires-Dist: dash; extra == "apps"
Provides-Extra: kafka
Requires-Dist: kafka-python; extra == "kafka"
Provides-Extra: mqtt
Requires-Dist: paho-mqtt; extra == "mqtt"
Provides-Extra: mongodb
Requires-Dist: pymongo>=3.2.2; extra == "mongodb"
Requires-Dist: dnspython; extra == "mongodb"
Provides-Extra: omegaml
Requires-Dist: pymongo>=3.2.2; extra == "omegaml"
Requires-Dist: dnspython; extra == "omegaml"
Requires-Dist: omegaml[client]>=0.15.3; extra == "omegaml"
Provides-Extra: all
Requires-Dist: kafka-python; extra == "all"
Requires-Dist: paho-mqtt; extra == "all"
Requires-Dist: pymongo>=3.2.2; extra == "all"
Requires-Dist: dnspython; extra == "all"
Requires-Dist: flask; extra == "all"
Requires-Dist: dash; extra == "all"
Provides-Extra: dev
Requires-Dist: kafka-python; extra == "dev"
Requires-Dist: paho-mqtt; extra == "dev"
Requires-Dist: pymongo>=3.2.2; extra == "dev"
Requires-Dist: dnspython; extra == "dev"
Requires-Dist: omegaml[client]>=0.15.3; extra == "dev"
Requires-Dist: pytest; extra == "dev"
Requires-Dist: twine; extra == "dev"
Requires-Dist: flake8; extra == "dev"
Requires-Dist: bumpversion; extra == "dev"
Requires-Dist: build; extra == "dev"
Dynamic: author
Dynamic: author-email
Dynamic: description
Dynamic: description-content-type
Dynamic: home-page
Dynamic: license
Dynamic: license-file
Dynamic: provides-extra
Dynamic: requires-dist
Dynamic: summary
